{
    "general": {
        "vendorName": "Albelli",
        "navigateAwayMessage": "Si abandonas esta página, se perderán todos los cambios. ¿Estás seguro que deseas cerrar el {0}?",
        "title": "Foto decoración",
        "productSelectorTitle": "{0}",
        "error": "Se ha producido un error",
        "warning": "advertencia",
        "close": "OK",
        "loading": "Cargando.",
        "productSpecificationTitle": "Especificaciones:",
        "productSpecificationSize": "Talla",
        "productSpecificationPrice": "Precio",
        "productSpecificationPriceText1": "{0} (excl.",
        "productSpecificationPricePrice": "gastos de envío",
        "productSpecificationPriceText2": ")",
        "yes": "Sí",
        "no": "No",
        "add": "Añadir",
        "cancel": "Cancelar",
        "notificationTitle": "",
        "canvas": "Lienzos",
        "perspex": "Foto en metacrilato",
        "phonecase": "Carcasas",
        "aluminium": "Foto en aluminio",
        "editor": "editor de {0}",
        "calendar": "Calendarios",
        "month": "Mes",
        "year": "Año",
        "event": "Evento",
        "events": "Eventos",
        "date": "Fecha"
    },
    "home": {
        "title": "{0}",
        "nextStepButton": "Crear ahora",
        "caption": "",
        "previousProductButton": "Anterior",
        "nextProductButton": "Siguiente"
    },
    "edit": {
        "selectFileType": "Selecciona una foto",
        "nextStepButton": "Siguiente",
        "marginTooltip": "este es el margen de plegado",
        "lowQualityTooltip": "la calidad es demasiado baja para el marco utilizado",
        "photoQualityIndicatorHeaderLabel": "Calidad:",
        "photoQualityIndicatorLabel": "{0}",
        "photoQualityIndicatorTooltipLow": "La calidad de la foto es demasiado baja para garantizar un resultado óptimo. ¿Quieres continuar de todos modos?",
        "photoQualityIndicatorTooltipMedium": "La calidad de la foto no es suficiente para garantizar un resultado óptimo. ¿Quieres continuar de todos modos?",
        "photoQualityIndicatorTooltipHigh": "La calidad de la foto es buena.",
        "photoQualityIndicatorTooltipExcellent": "La calidad de la foto es excelente.",
        "uploadPhotoLabel": "Selecciona una foto",
        "uploadDifferentPhotoLabel": "Selecciona una foto diferente",
        "uploadPhotoButtonTooltip": "Haz clic aquí para añadir una foto",
        "rotateWarning": "Please rotate your device",
        "emptyPlaceholder": {
            "title": "IMAGEN",
            "text": "Haz clic o arrastra aquí para añadir"
        },
        "photoTray": {
            "addPhotoButton": {
                "text": "Añadir una nueva foto (s)",
                "tooltip": "Haz clic aquí para añadir una foto"
            }
        },
        "layout": {
            "title": "",
            "subtitle": ""
        },
        "tabs": {
            "months": "Meses",
            "photo": "Tus fotos",
            "foreground": "",
            "background": "Fondos",
            "tooltrayshow": "Mostrar",
            "tooltrayhide": "Esconder",
            "decoration": "Marcos",
            "layout": "Distribuciones",
            "spacing": {
                "labels": {
                    "inner": "Espaciado interior: {0}",
                    "inner-small": "Interior: {0}",
                    "outer": "Espaciado exterior: {0}",
                    "outer-small": "Exterior: {0}"
                },
                "title": "Espaciado"
            }
        },
        "photoQualityIndicatorLow": "Insuficiente",
        "photoQualityIndicatorMedium": "Moderada",
        "photoQualityIndicatorHigh": "Buena",
        "photoQualityIndicatorExcellent": "Excelente",
        "navigation": {
            "back": "Volver",
            "back-small": "Volver",
            "next": "Añadir a la cesta",
            "next-small": "Pedir"
        },
        "photoTools": {
            "close": "Anterior",
            "close-small": "Anterior",
            "delete": "Borrar",
            "delete-small": "Borrar",
            "effects": {
                "close": "Anterior",
                "close-small": "Anterior",
                "grayscale": "",
                "grayscale-small": "",
                "label": "Filtros",
                "label-small": "Filtros",
                "original": "",
                "original-small": "",
                "sepia": "",
                "sepia-small": ""
            },
            "mirror": "Voltear",
            "mirror-small": "Voltear",
            "rotate": "Rotar",
            "rotate-small": "Rotar",
            "swap": "Cambiar",
            "swap-small": "Cambiar",
            "zoom": {
                "label": "Zoom",
                "label-small": "Zoom",
                "tooltips": {
                    "in": "",
                    "out": "",
                    "slider": ""
                }
            }
        },
        "cover": "Cubierta",
        "pickStart": "Elige una fecha de inicio",
        "addAllOption": "Sí, añadir todos los eventos a mi calendario",
        "selectAll": "Seleccionar todo",
        "selectNone": "No seleccionar nada",
        "tabEvents": "Tus eventos",
        "tabHolidays": "Tus días festivos",
        "addEvent": "Añade tu evento",
        "addHoliday": "Añade un día festivo",
        "eventName": "Nombre del evento",
        "updateButton": "Actualizar calendario"
    },
    "save": {
        "saveText": "Guardar",
        "saveBody": "Ponle un nombre a tu producto y guárdalo."
    },
    "load": {
        "loadText": "Abrir",
        "loadBody": "Abrir un fotolibro guardado",
        "created": "",
        "modified": ""
    },
    "order": {
        "orderTitle": "Tu pedido",
        "invoiceTitle": "Resumen del pedido",
        "numberOfCopiesDescription": "(selecciona aquí el número de copias)",
        "subTotal": "Subtotal",
        "shipping": "Gastos de envío",
        "invoiceDiscount": "Descuento",
        "total": "Total",
        "promoTitle": "Código promocional",
        "promoDescription": "¿Tienes un código promocional? Introduce aquí el código.",
        "applyPromoCodeButton": "Aplicar",
        "deliveryAddressTitle": "Dirección de envío",
        "updateDeliveryAddressButton": "Actualizar",
        "previousStepButton": "Volver",
        "submitButton": "Realizar el pedido",
        "promotionPopupTitle": "Código promocional no válido",
        "promotionPopupSubtitle": "El código promocional introducido no es válido. Introduce un código válido.",
        "promotionPopupEnterPromotionCodeLabel": "Código promocional:",
        "promotionPopupCancelLabel": "Hacer un pedido sin código promocional",
        "promotionPopupSubmitLabel": "Enviar",
        "navigation": {
            "back": "Anterior",
            "back-small": "Anterior",
            "next": "Siguente",
            "next-small": "Siguente"
        }
    },
    "upload": {
        "uploading": "Finalizando pedido. Por favor espera. %3%",
        "busyUploadingLabel": "Estamos finalizando tu pedido. Esto no debería de tardar mucho tiempo. Una vez finalizada la carga, te redirigimos a tu cesta."
    },
    "help": {
        "helpTitle": "Atención al cliente",
        "helpText": "Consulta las preguntas frecuentes",
        "helpURL": "http://www.albelli.es/atencion-al-cliente",
        "moreOptionsUrl": ""
    },
    "alerts": {
        "invalidPromotionCode": "Lo sentimos, el código promocional no es válido."
    },
    "warnings": {
        "qualityTitle": "Atención: la calidad de la imagen es demasiado baja.",
        "qualitySubtitle": "Puedes continuar con tu pedido, pero debes tener en cuenta que calidad de la imagen no es óptima para el producto elegido.",
        "qualityOptionsTitle": "",
        "qualityOptions": "",
        "qualityFooter": "Para obtener más consejos, por favor ponte en contacto con nuestro <a href=\"{CUSTOMER_SERVICE}\" target=\"_blank\">servicio de atención al cliente<\/a>.",
        "qualityButtonCancel": "Volver al editor",
        "qualityButtonProceed": "Quiero continuar de todos modos",
        "layouts": {
            "lessPlaceholdersThanPhotos": {
                "message": "Has elegido una distribución que contiene menos fotos que la página actual. Si continúas, {0} foto/s se eliminarán de la página actual. ¿Quieres continuar?"
            }
        }
    },
    "dialogs": {
        "browser": {
            "browserWarning": "Desafortunadamente tu navegador no soporta todas las opciones para la creación de este producto. Por favor, instale Safari, Chrome, Firefox o una versión más reciente de Internet Explorer (10 o superior) y vuelva a empezar, o continúe con opciones limitadas.",
            "chromeInstall": "Instalar Chrome",
            "gotoFlash": "Continuar de todos modos"
        },
        "features": {
            "reducedFeatures": "Bienvenido al Editor de Albelli para Calendarios personalizados. Arrastra y suelta tus fotos y fondos, y agrega eventos y días festivos. Disponemos de más opciones creativas en nuestro editor para dispositivos de escritorio y portátiles.",
            "continue": "Crea tu calendario"
        }
    },
    "errors": {
        "errorBootstrapping": "Se ha presentado un error durante el inicio. Ponte en contacto con el servicio de atención al cliente o inténtalo de nuevo más tarde.",
        "countryList": "SE ha presentado un error al cargar la lista de países. Ponte en contacto con el servicio de atención al cliente o inténtalo de nuevo más tarde.",
        "lowMemoryWarning": "Parece que tu dispositivo se está quedando sin memoria. Por favor, cierra todas las aplicaciones en ejecución y vuelve a intentarlo.",
        "defaultPrice": "Se ha presentado un error al cargar la información de precios. Ponte en contacto con el servicio de atención al cliente o inténtalo de nuevo más tarde.",
        "loadPhotoBitmapData": "Se ha presentado un error durante la carga de la foto. Ponte en contacto con el servicio de atención al cliente o inténtalo de nuevo más tarde.",
        "loadBigPhoto": "Se ha producido un error al cargar la foto. Por favor, reduce las dimensiones a un máximo de 8000 x 8000 píxeles y vuelve a intentarlo.",
        "creatingPhoto": "Se ha presentado un error durante el procesamiento de la foto. Ponte en contacto con el servicio de atención al cliente o inténtalo de nuevo más tarde.",
        "photoRegistration": "Se ha presentado un error durante el procesamiento de la foto. Ponte en contacto con el servicio de atención al cliente o inténtalo de nuevo más tarde.",
        "addPhotoToPhotoPlaceholderEmpty": "Se ha presentado un error al colocar la foto en el marco. Ponte en contacto con el servicio de atención al cliente o inténtalo de nuevo más tarde.",
        "addPhotoToPhotoPlaceholder": "Se ha presentado un error al colocar la foto en el marco. Ponte en contacto con el servicio de atención al cliente o inténtalo de nuevo más tarde.",
        "startUploadPhoto": "Se ha presentado un error al iniciar la carga de la foto. Ponte en contacto con el servicio de atención al cliente o inténtalo de nuevo más tarde.",
        "setPhotoCanvas": "Se produjo un error al cambiar entre los productos. Ponte en contacto con el servicio de atención al cliente o inténtalo de nuevo más tarde.",
        "createCustomer": "Se ha presentado un error al procesar los datos de cliente. Ponte en contacto con el servicio de atención al cliente o inténtalo de nuevo más tarde.",
        "createOrder": "Se ha presentado un error al crear los datos de la factura. Ponte en contacto con el servicio de atención al cliente o inténtalo de nuevo más tarde.",
        "getInvoice": "Se ha presentado un error al cargar los datos de la factura. Ponte en contacto con el servicio de atención al cliente o inténtalo de nuevo más tarde.",
        "sendOrder": "Se ha presentado un error durante el envío del pedido. Ponte en contacto con el servicio de atención al cliente o inténtalo de nuevo más tarde.",
        "getPaymentUrl": "Se ha presentado un error al cargar la información de pago. Ponte en contacto con el servicio de atención al cliente o inténtalo de nuevo más tarde.",
        "browserWarning": "Lo sentimos, no se puede diseñar un producto usando este navegador. Por favor, instala el navegador Google Chrome para poder continuar."
    },
    "validations": {
        "emailMissingAtSign": "Falta el símbolo @ en la dirección de correo electrónico.",
        "emailMissingPeriodInDomain": "Falta un punto (.) en la dirección de correo electrónico.",
        "emailDomainInvalidFormatted": "El nombre de dominio de la dirección de correo electrónico es inválido.",
        "emailTooManyAtCharacters": "La dirección de correo electrónico tiene demasiados (@).",
        "emailConsecutivePeriodsInDomain": "El correo electrónico contiene varios puntos seguidos (.).",
        "emailInvalidChars": "El correo electrónico contiene caracteres inválidos.",
        "emailInvalidIp": "La dirección ip en el dominio de la dirección de correo electrónico es inválida.",
        "emailMissingUsername": "Falta el nombre de usuario en la dirección de correo electrónico.",
        "emailRequired": "campo obligatorio",
        "textRequired": "campo obligatorio",
        "textTooLong": "Has alcanzado el número máximo de caracteres.",
        "zipcodeRequired": "campo obligatorio",
        "zipcodeInvalid": "código postal inválido, utilice el formato:"
    },
    "layout": {
        "navigation": {
            "back": "",
            "back-small": "",
            "next": "",
            "next-small": ""
        },
        "subtitle": "Elige el número de fotos",
        "title": "Selecciona una distribución"
    },
    "preview": {
        "button": "Vista previa",
        "buttonBack": "Volver a editar",
        "close": "Editar producto",
        "options": {
            "context": "Ver en pared",
            "full": "Vista completa"
        },
        "title": "Opciones de vista previa:"
    },
    "calendar": {
        "months": {
            "m0": "Enero",
            "m1": "Febrero",
            "m2": "Marzo",
            "m3": "Abril",
            "m4": "Mayo",
            "m5": "Junio",
            "m6": "Julio",
            "m7": "Agosto",
            "m8": "Septiembre",
            "m9": "Octubre",
            "m10": "Noviembre",
            "m11": "Diciembre"
        },
        "days": {
            "mon": "Lunes",
            "tue": "Martes",
            "wen": "Miércoles",
            "thu": "Jueves",
            "fri": "Viernes",
            "sat": "Sábado",
            "sun": "Domingo",
            "short": {
                "mon": "L",
                "tue": "M",
                "wed": "X",
                "thu": "J",
                "fri": "V",
                "sat": "S",
                "sun": "D"
            }
        },
        "warnings": {
            "eventMax": "No es posible añadir más de {0} eventos en cada fecha"
        }
    },
    "customer": {
        "customerCity": "",
        "customerCountryCode": "",
        "customerEmail": "",
        "customerFirstname": "",
        "customerHouseNumber": "",
        "customerLastname": "",
        "customerMiddlename": "",
        "customerPhone": "",
        "customerStreet": "",
        "customerZip": "",
        "nextStepButton": "",
        "previousStepButton": "",
        "subscribeToNewsletter": "",
        "title": ""
    },
    "months": {
        "month0": "",
        "month1": "",
        "month2": "",
        "month3": "",
        "month4": "",
        "month5": "",
        "month6": "",
        "month7": "",
        "month8": "",
        "month9": "",
        "month10": "",
        "month11": ""
    }
}
